design.sv
// Code your design here
module RTDC(input rst,clk,output reg [6:0] hr_m,hr_l,min_m,min_l,sec_m,sec_l);
reg[3:0]count1,count2,count3,count4,count5,count6;
always@(negedge clk)
begin
if(rst==1)
begin
count1<=0;
count2<=0;
count3<=0;
count4<=0;
count5<=0;
count6<=0;
end
else 
begin
count2<=count2+1;
if(count2==9)
begin
count2<=0;
count1<=count1+1;
if({count1,count2}==59)
begin
{count1,count2}<=0;
count4<=count4+1;
if(count4==9)
begin
count4<=0;
count3<=count3+1;
if({count3,count4}==59)
begin
{count3,count4}<=0;
count6<=count6+1;
if(count6==9)
begin
count6<=0;
count5=count5+1;
if({count5,count6}==23)
begin
{count5,count6}<=0;
end
end
end
end
end
end
end
end
always@(count1 or count2 or count3 or count4 or count5 or count6)
begin
case(count1)
0:sec_m=7'b0000001;
1:sec_m=7'b1001111;
2:sec_m=7'b0010010;
3:sec_m=7'b0000110;
4:sec_m=7'b1001100;
5:sec_m=7'b0100100;
6:sec_m=7'b0100000;
7:sec_m=7'b0001111;
8:sec_m=7'b0000000;
9:sec_m=7'b0000100;
default:sec_m=7'b1111111;
endcase
case(count2)
0:sec_l=7'b0000001;
1:sec_l=7'b1001111;
2:sec_l=7'b0010010;
3:sec_l=7'b0000110;
4:sec_l=7'b1001100;
5:sec_l=7'b0100100;
6:sec_l=7'b0100000;
7:sec_l=7'b0001111;
8:sec_l=7'b0000000;
9:sec_l=7'b0000100;
default:sec_l=7'b1111111;
endcase
case(count3)
0:min_m=7'b0000001;
1:min_m=7'b1001111;
2:min_m=7'b0010010;
3:min_m=7'b0000110;
4:min_m=7'b1001100;
5:min_m=7'b0100100;
6:min_m=7'b0100000;
7:min_m=7'b0001111;
8:min_m=7'b0000000;
9:min_m=7'b0000100;
default:min_m=7'b1111111;
endcase
case(count4)
0:min_l=7'b0000001;
1:min_l=7'b1001111;
2:min_l=7'b0010010;
3:min_l=7'b0000110;
4:min_l=7'b1001100;
5:min_l=7'b0100100;
6:min_l=7'b0100000;
7:min_l=7'b0001111;
8:min_l=7'b0000000;
9:min_l=7'b0000100;
default:min_m=7'b1111111;
endcase
case(count5)
0:hr_m=7'b0000001;
1:hr_m=7'b1001111;
2:hr_m=7'b0010010;
3:hr_m=7'b0000110;
4:hr_m=7'b1001100;
5:hr_m=7'b0100100;
6:hr_m=7'b0100000;
7:hr_m=7'b0001111;
8:hr_m=7'b0000000;
9:hr_m=7'b0000100;
default:hr_m=7'b1111111;
endcase
case(count6)
0:hr_l=7'b0000001;
1:hr_l=7'b1001111;
2:hr_l=7'b0010010;
3:hr_l=7'b0000110;
4:hr_l=7'b1001100;
5:hr_l=7'b0100100;
6:hr_l=7'b0100000;
7:hr_l=7'b0001111;
8:hr_l=7'b0000000;
9:hr_l=7'b0000100;
default:hr_l=7'b1111111;
endcase
end
endmodule

testbench.sv
// Code your testbench here
// or browse Examples
module test;
reg clk,rst;
wire[6:0]hr_m,hr_l,min_m,min_l,sec_m,sec_l;
RTDC dut(rst,clk,sec_m,sec_l,min_m,min_l,hr_m,hr_l);
initial begin
clk=0;
rst=1;
#10 rst=0;
#500 $finish();
end
always #10 clk=~clk;
 initial begin
   $dumpfile("rtdc.vcd");
   $dumpvars;
 end
endmodule

rtdc.vcd
$date
	Thu Mar 30 06:37:20 2023
$end
$version
	Icarus Verilog
$end
$timescale
	1s
$end
$scope module test $end
$var wire 7 ! hr_l [6:0] $end
$var wire 7 " hr_m [6:0] $end
$var wire 7 # min_l [6:0] $end
$var wire 7 $ min_m [6:0] $end
$var wire 7 % sec_l [6:0] $end
$var wire 7 & sec_m [6:0] $end
$var reg 1 ' clk $end
$var reg 1 ( rst $end
$scope module dut $end
$var wire 1 ) clk $end
$var wire 1 * rst $end
$var reg 4 + count1 [3:0] $end
$var reg 4 , count2 [3:0] $end
$var reg 4 - count3 [3:0] $end
$var reg 4 . count4 [3:0] $end
$var reg 4 / count5 [3:0] $end
$var reg 4 0 count6 [3:0] $end
$var reg 7 1 hr_l [6:0] $end
$var reg 7 2 hr_m [6:0] $end
$var reg 7 3 min_l [6:0] $end
$var reg 7 4 min_m [6:0] $end
$var reg 7 5 sec_l [6:0] $end
$var reg 7 6 sec_m [6:0] $end
$upscope $end
$upscope $end
$enddefinitions $end
#0
$dumpvars
b1 6
b1 5
b1 4
b1 3
b1 2
b1 1
b0 0
b0 /
b0 .
b0 -
b0 ,
b0 +
1*
0)
1(
0'
b1 &
b1 %
b1 $
b1 #
b1 "
b1 !
$end
#10
1'
1)
0(
0*
#20
b1001111 5
b1001111 !
b1 ,
0'
0)
#30
1'
1)
#40
b10010 5
b10010 !
b10 ,
0'
0)
#50
1'
1)
#60
b110 5
b110 !
b11 ,
0'
0)
#70
1'
1)
#80
b1001100 5
b1001100 !
b100 ,
0'
0)
#90
1'
1)
#100
b100100 5
b100100 !
b101 ,
0'
0)
#110
1'
1)
#120
b100000 5
b100000 !
b110 ,
0'
0)
#130
1'
1)
#140
b1111 5
b1111 !
b111 ,
0'
0)
#150
1'
1)
#160
b0 5
b0 !
b1000 ,
0'
0)
#170
1'
1)
#180
b100 5
b100 !
b1001 ,
0'
0)
#190
1'
1)
#200
b1 5
b1 !
b1001111 6
b1001111 "
b1 +
b0 ,
0'
0)
#210
1'
1)
#220
b1001111 5
b1001111 !
b1 ,
0'
0)
#230
1'
1)
#240
b10010 5
b10010 !
b10 ,
0'
0)
#250
1'
1)
#260
b110 5
b110 !
b11 ,
0'
0)
#270
1'
1)
#280
b1001100 5
b1001100 !
b100 ,
0'
0)
#290
1'
1)
#300
b100100 5
b100100 !
b101 ,
0'
0)
#310
1'
1)
#320
b100000 5
b100000 !
b110 ,
0'
0)
#330
1'
1)
#340
b1111 5
b1111 !
b111 ,
0'
0)
#350
1'
1)
#360
b0 5
b0 !
b1000 ,
0'
0)
#370
1'
1)
#380
b100 5
b100 !
b1001 ,
0'
0)
#390
1'
1)
#400
b1 5
b1 !
b10010 6
b10010 "
b10 +
b0 ,
0'
0)
#410
1'
1)
#420
b1001111 5
b1001111 !
b1 ,
0'
0)
#430
1'
1)
#440
b10010 5
b10010 !
b10 ,
0'
0)
#450
1'
1)
#460
b110 5
b110 !
b11 ,
0'
0)
#470
1'
1)
#480
b1001100 5
b1001100 !
b100 ,
0'
0)
#490
1'
1)
#500
b100100 5
b100100 !
b101 ,
0'
0)
